README.md
setup.py
Flask_GraphQL_Auth.egg-info/PKG-INFO
Flask_GraphQL_Auth.egg-info/SOURCES.txt
Flask_GraphQL_Auth.egg-info/dependency_links.txt
Flask_GraphQL_Auth.egg-info/requires.txt
Flask_GraphQL_Auth.egg-info/top_level.txt
flask_graphql_auth/__init__.py
flask_graphql_auth/decorators.py
flask_graphql_auth/exceptions.py
flask_graphql_auth/fields.py
flask_graphql_auth/main.py
flask_graphql_auth/util.py