Metadata-Version: 1.0
Name: Flask-GraphQL-Auth
Version: 1.1.1
Summary: JWT library for Flask-GraphQL
Home-page: https://github.com/devArtoria/flask-graphql-auth
Author: devArtoria
Author-email: artoria@artoria.us
License: MIT
Keywords: jwt,auth,graphql
Platform: UNKNOWN
